{
  "updated": "2026-05-27T17:44:12.384Z",
  "week": [
    {
      "day": "Maanantai 25.5.2026",
      "menu": [
        "Sitruunainen parsakeitto (L+G) krutonki (M)",
        "Uunissa paahdettua lohta salsa-verde kastikkeella (M+G+VS) parmesaani-kermaperunat (L+G)",
        "Grillattuja porsaan noisetteja dijon-sinappikastikkeella (L+G+VS)",
        "Mausteinen kana-biryani intialaiseen tapaan (M+G+VS) raitakastike (L+G)",
        "Chili-soijakaramelli-tofua ja wokattuja kasviksia (VE+G+VS) basmatiriisi (VE+G)",
        "Marjapiirakka (L) vaniljakastike (L+G)"
      ]
    },
    {
      "day": "Tiistai 26.5.2026",
      "menu": [
        "Chilillä höystetty Koskenlaskijan porkkanakeitto (L+G)",
        "Factoryn lihapullat savujuustokastikkeessa (L+G) voilla höystetty perunamuusi (L+G)",
        "Rapeaksi paistettua tempura-turskaa (L) tartarkastike (L+G)",
        "Itse tehdyt pinaattiohukaiset (L) puolukkahillo (VE+G)",
        "Juurespyttipannu vegaanisilla MUU-naggeilla ja karamellisoidulla sipulilla (VE+G+VS)",
        "Factoryn jäätelöbaari (L+G)"
      ]
    },
    {
      "day": "Keskiviikko 27.5.2026",
      "menu": [
        "Kermainen lehtikaalikeitto (L+G) paahdetut kurpitsansiemenet",
        "Hitaasti kypsennettyä porsaankylkeä Whiskey-BBQ -kastikkeella (M+G) uunissa paahdetut cajunperunat (M+G)",
        "Rapeat gluteenittomat kanan wingsit (L+G) sweet chili -dippi (VE+G+VS)",
        "Piri-piri scampi pasta tuoreella rucolalla ja parmesanjuustolla (VL+VS)",
        "Palak Tofu – itämainen pinaatticurry tuoreella korianterilla (VE+G+VS) basmatiriisi (VE+G)",
        "Talon kirsikka-tiramisu (VL)"
      ]
    },
    {
      "day": "Torstai 28.5.2026",
      "menu": [
        "Savupotka-hernekeitto (M+G) pilkottua sipulia (VE+G)",
        "Mureaa broilerin rintafilettä chilillä maustetulla mango-kookoskermakastikkeella (M+G) basmatiriisi (VE+VS+G)",
        "Rapeaksi paistettua tex mex -seitiä basilika-vinegretti -glaseerauksella (VL) lime-korianteri jogurtti (L+G+VS)",
        "Mausteinen gnocchipannu kirsikkatomaateilla ja Gold &amp; Green -suikaleilla (VE+G+VS)",
        "Factoryn letut (L) mansikkahillo (VE+G) vaniljavaahto (L+G) jäätelö (L+G)",
        "Gluteenittomat letut ja vegaaniset letut (VE+G) (Pyydetään erikseen keittiöstä)"
      ]
    },
    {
      "day": "Perjantai 29.5.2026",
      "menu": [
        "Thaimaalainen rapu-kookoskeitto (M+G+VS)",
        "Rapeat paneroidut porsaanleikkeet (M) bearnaisekastike (VL+G) annanperunat (VE+G+VS)",
        "Kanan paistileike chimichurri-glaseerauksella (M+G+VS) basmatiriisi (VE+G)",
        "Kikherne–tofumuru -kasvispata kookos–tomaattikastikkeessa (VE+G)",
        "Hunajakakkupalat (VL) suklaavanukas (L+G)"
      ]
    }
  ]
}