{
  "updated": "2026-05-11T16:17:19.419Z",
  "week": [
    {
      "day": "Keskiviikko 13.5.2026",
      "menu": [
        "Savupotka hernekeittoa (M+G) pilkottua sipulia (VE+G)",
        "Tee-se-itse BBQ-pekonihampurilaiset, pihvi (M+G+VS), sämpylä (VE) ranskalaiset (VE+G) marinoitu sipuli (VE+G) cheddarjuustokastike (L+G) aioli (VE+G+VS) suolakurkku (VE)",
        "Grillatut yrtti-marinoidut kanan paistileikkeet paahdetuilla paprikoilla (M+G) basmatiriisi (VE+G)",
        "tomaattinen salsa (VE+VS)",
        "Vegaaninen chili sin carne kaura-kasvis -proteiinisuikaleilla (VE+G+VS)",
        "Factoryn letut (L) mansikkahillo (VE+G) vaniljavaahto (L+G) jäätelö (L+G)",
        "Gluteenittomat letut ja vegaaniset letut (VE+G) (Pyydetään erikseen keittiöstä)"
      ]
    },
    {
      "day": "Torstai 14.5.2026",
      "menu": [
        "Hyvää Helatorstaita ! Ravintola on tänään kiinni."
      ]
    },
    {
      "day": "Perjantai 15.5.2026",
      "menu": [
        "Siskonmakkarakeitto (M+G)",
        "Factoryn lihapullat savupekonikastikkeessa (L+G+VS) grillatut lohkoperunat (VE+G)",
        "Rapeaksi paistettua tex mex -seitiä sitruunavinegretti-glaseerauksella (VL) remouladedippi (VE+G+VS)",
        "Mausteinen intialainen kana-biryani tuoreella korianterilla (M+G+VS)",
        "Vegaanista chili-marinoitua tofua ja grillattuja kasviksia teriyakikastikkeella (VE+G+VS)",
        "Mokkapala (L) ja vaniljakastiketta (L+G)"
      ]
    }
  ]
}